notepads/__init__.py
notepads/_core/__init__.py
notepads/_core/_directory.py
notepads/_core/_file.py
notepads/_core/_folder.py
notepads/_core/_note.py
notepads-2023.12.10.dist-info/METADATA
notepads-2023.12.10.dist-info/WHEEL
notepads-2023.12.10.dist-info/top_level.txt
notepads-2023.12.10.dist-info/RECORD
