Metadata-Version: 2.1
Name: notepads
Version: 2023.12.10
Summary: Create runtime folders, files, and code notes. All stored in notepads environment.
Home-page: https://github.com
Author: notepads
Author-email: toolkitr.email@gmail.com
License: MIT
Keywords: entry,entries
Classifier: Development Status :: 1 - Planning
Classifier: Development Status :: 2 - Pre-Alpha
Classifier: Development Status :: 3 - Alpha
Classifier: Development Status :: 4 - Beta
Classifier: Development Status :: 5 - Production/Stable
Classifier: Intended Audience :: Developers
Classifier: Topic :: Software Development :: Build Tools
Classifier: License :: OSI Approved :: MIT License
Classifier: Programming Language :: Python :: 3
Classifier: Programming Language :: Python :: 3.7
